LICENSE
pipelime/__init__.py
pipelime/choixe/__init__.py
pipelime/choixe/xconfig.py
pipelime/choixe/ast/__init__.py
pipelime/choixe/ast/nodes.py
pipelime/choixe/ast/parser.py
pipelime/choixe/utils/__init__.py
pipelime/choixe/utils/common.py
pipelime/choixe/utils/imports.py
pipelime/choixe/utils/io.py
pipelime/choixe/utils/rand.py
pipelime/choixe/visitors/__init__.py
pipelime/choixe/visitors/decoder.py
pipelime/choixe/visitors/inspector.py
pipelime/choixe/visitors/processor.py
pipelime/choixe/visitors/processor_ui.py
pipelime/choixe/visitors/unparser.py
pipelime/choixe/visitors/walker.py
pipelime/cli/__init__.py
pipelime/cli/main.py
pipelime/cli/parser.py
pipelime/cli/pretty_print.py
pipelime/cli/subcommands.py
pipelime/cli/utils.py
pipelime/cli/tui/__init__.py
pipelime/cli/tui/tui.css
pipelime/cli/tui/tui.py
pipelime/cli/tui/utils.py
pipelime/commands/__init__.py
pipelime/commands/general.py
pipelime/commands/interfaces.py
pipelime/commands/piper.py
pipelime/commands/resume.py
pipelime/commands/shell.py
pipelime/commands/split_ops.py
pipelime/commands/tempman.py
pipelime/commands/toy_dataset.py
pipelime/items/__init__.py
pipelime/items/base.py
pipelime/items/binary_item.py
pipelime/items/image_item.py
pipelime/items/metadata_item.py
pipelime/items/model3d_item.py
pipelime/items/numpy_item.py
pipelime/items/pickle_item.py
pipelime/piper/__init__.py
pipelime/piper/checkpoint.py
pipelime/piper/graph.py
pipelime/piper/model.py
pipelime/piper/drawing/__init__.py
pipelime/piper/drawing/base.py
pipelime/piper/drawing/factory.py
pipelime/piper/drawing/graphviz.py
pipelime/piper/drawing/mermaid.py
pipelime/piper/executors/__init__.py
pipelime/piper/executors/base.py
pipelime/piper/executors/factory.py
pipelime/piper/executors/naive.py
pipelime/piper/parsers/__init__.py
pipelime/piper/parsers/base.py
pipelime/piper/parsers/choixe_parser.py
pipelime/piper/parsers/factory.py
pipelime/piper/progress/__init__.py
pipelime/piper/progress/model.py
pipelime_python-2.2.0.dist-info/METADATA
pipelime_python-2.2.0.dist-info/WHEEL
pipelime_python-2.2.0.dist-info/entry_points.txt
pipelime_python-2.2.0.dist-info/licenses/LICENSE
pipelime_python-2.2.0.dist-info/RECORD
