Metadata-Version: 2.4
Name: pipelime-python
Version: 2.2.0
Summary: Data workflows, cli and dataflow automation.
Project-URL: Source, https://github.com/eyecan-ai/pipelime-python
Project-URL: Issues, https://github.com/eyecan-ai/pipelime-python/issues
Project-URL: Documentation, http://pipelime-python.readthedocs.io/
Author-email: "Eyecan.ai" <info@eyecan.ai>
License: GNU General Public License v3 (GPLv3)
License-File: LICENSE
Keywords: dataflow,dataset,orchestration,pipelime,workflow
Classifier: Development Status :: 5 - Production/Stable
Classifier: Intended Audience :: Developers
Classifier: Intended Audience :: Science/Research
Classifier: License :: OSI Approved :: GNU General Public License v3 (GPLv3)
Classifier: Natural Language :: English
Classifier: Operating System :: OS Independent
Classifier: Programming Language :: Python :: 3
Classifier: Programming Language :: Python :: 3.10
Classifier: Programming Language :: Python :: 3.11
Classifier: Programming Language :: Python :: 3.12
Classifier: Topic :: Scientific/Engineering
Classifier: Topic :: Software Development
Requires-Python: <3.13,>=3.10
Requires-Dist: albumentations>=1.0.0
Requires-Dist: astunparse
Requires-Dist: deepdiff
Requires-Dist: dictquery
Requires-Dist: filelock
Requires-Dist: imageio[ffmpeg,pyav]>=2.17.0
Requires-Dist: loguru
Requires-Dist: networkx
Requires-Dist: numpy
Requires-Dist: pydantic<3,>=1.10.17
Requires-Dist: pydash
Requires-Dist: python-box
Requires-Dist: pyyaml
Requires-Dist: pyzmq
Requires-Dist: requests
Requires-Dist: rich>=9.9.0
Requires-Dist: schema
Requires-Dist: textual>=0.26.0
Requires-Dist: tifffile
Requires-Dist: toml
Requires-Dist: tqdm
Requires-Dist: trimesh
Requires-Dist: typer>=0.6
Provides-Extra: build
Requires-Dist: build; extra == 'build'
Requires-Dist: hatch; extra == 'build'
Provides-Extra: dev
Requires-Dist: black; extra == 'dev'
Requires-Dist: flake8; extra == 'dev'
Requires-Dist: pylama; extra == 'dev'
Provides-Extra: docs
Requires-Dist: myst-parser==0.18.0; extra == 'docs'
Requires-Dist: sphinx-immaterial==0.11.3; extra == 'docs'
Requires-Dist: sphinx==5.1.1; extra == 'docs'
Requires-Dist: sphinxcontrib-mermaid==0.7.1; extra == 'docs'
Provides-Extra: draw
Requires-Dist: pygraphviz; extra == 'draw'
Provides-Extra: tests
Requires-Dist: pytest; extra == 'tests'
Requires-Dist: pytest-asyncio; extra == 'tests'
Requires-Dist: pytest-cov; extra == 'tests'
Requires-Dist: tox; extra == 'tests'
